pyvv/pyvv.py
pyvv-1.0.0.dist-info/METADATA
pyvv-1.0.0.dist-info/WHEEL
pyvv-1.0.0.dist-info/entry_points.txt
pyvv-1.0.0.dist-info/top_level.txt
pyvv-1.0.0.dist-info/RECORD
