Metadata-Version: 2.4
Name: pyvv
Version: 1.0.0
Summary: Python 多版本
Author: jiaosenvip
Author-email: jiaosenvip <jiaosenvip@163.com>
License: MIT
Project-URL: Homepage, https://github.com/jiaosenvip/pyvv
Project-URL: Documentation, https://github.com/jiaosenvip/pyvv/wiki
Requires-Python: >=3.11
Requires-Dist: rich>=13.9.0
Requires-Dist: uv>=0.6.9
